{
  "checked_at": "2026-05-15T07:49:21.895841+00:00",
  "flowguard_explorer": {
    "dead_branch_count": 0,
    "exception_branch_count": 0,
    "ok": true,
    "reachability_failure_count": 0,
    "reachability_failures": [],
    "summary": "sequences=2 initial_states=1 traces=45",
    "violation_count": 0
  },
  "hazard_checks": {
    "failures": [],
    "hazards": {
      "controller_owns_router_dependencies": {
        "detected": true,
        "expected_failure": "Controller table owns Router dependency metadata",
        "failures": [
          "Controller table owns Router dependency metadata"
        ],
        "state": {
          "barrier_active": false,
          "continuous_standby_row_present": false,
          "controller_action_table_exists": true,
          "controller_table_has_router_dependency_graph": true,
          "daemon_started": true,
          "daemon_tick_seconds": 1,
          "duplicate_controller_row_created": false,
          "enqueued_after_barrier": false,
          "foreground_controller_stopped_during_standby": false,
          "idempotency_key_used": false,
          "independent_controller_row_pending": false,
          "independent_row_enqueued": false,
          "live_wait_without_ordinary_controller_row": false,
          "next_independent_row_enqueued": false,
          "pm_activation_decision_accepted": false,
          "pm_activation_second_global_join_required": false,
          "pm_startup_activation_ack_clean": false,
          "pm_startup_activation_card_sent": false,
          "receipt_done": false,
          "reviewer_fact_report_recorded": false,
          "reviewer_startup_fact_review_started": false,
          "route_work_started": false,
          "router_marked_row_reconciled": false,
          "router_scheduler_table_exists": true,
          "router_table_has_dependency_metadata": true,
          "router_visible_postcondition_written": false,
          "scenario": "controller_owns_router_dependencies",
          "standby_codex_plan_item_in_progress": false,
          "standby_codex_plan_sync_required": false,
          "standby_completed_after_one_check": false,
          "standby_row_names_wait_target": false,
          "standby_row_stable_idempotency": false,
          "standby_strict_monitor_wait_policy": false,
          "standby_timeout_still_waiting_treated_as_completion": false,
          "startup_local_rows_clean": false,
          "startup_prep_acks_clean": false,
          "startup_prep_cards_sent": false,
          "startup_scope_active": true,
          "startup_scope_reconciliation_checked": false,
          "startup_scope_reconciliation_clean": false,
          "stateful_postcondition_required": false,
          "status": "rejected",
          "terminal_reason": "invalid"
        }
      },
      "daemon_duplicates_controller_row_on_retry": {
        "detected": true,
        "expected_failure": "daemon retry duplicated Controller row without deterministic idempotency",
        "failures": [
          "daemon retry duplicated Controller row without deterministic idempotency"
        ],
        "state": {
          "barrier_active": false,
          "continuous_standby_row_present": false,
          "controller_action_table_exists": true,
          "controller_table_has_router_dependency_graph": false,
          "daemon_started": true,
          "daemon_tick_seconds": 1,
          "duplicate_controller_row_created": true,
          "enqueued_after_barrier": false,
          "foreground_controller_stopped_during_standby": false,
          "idempotency_key_used": false,
          "independent_controller_row_pending": false,
          "independent_row_enqueued": true,
          "live_wait_without_ordinary_controller_row": false,
          "next_independent_row_enqueued": false,
          "pm_activation_decision_accepted": false,
          "pm_activation_second_global_join_required": false,
          "pm_startup_activation_ack_clean": false,
          "pm_startup_activation_card_sent": false,
          "receipt_done": false,
          "reviewer_fact_report_recorded": false,
          "reviewer_startup_fact_review_started": false,
          "route_work_started": false,
          "router_marked_row_reconciled": false,
          "router_scheduler_table_exists": true,
          "router_table_has_dependency_metadata": true,
          "router_visible_postcondition_written": false,
          "scenario": "daemon_duplicates_controller_row_on_retry",
          "standby_codex_plan_item_in_progress": false,
          "standby_codex_plan_sync_required": false,
          "standby_completed_after_one_check": false,
          "standby_row_names_wait_target": false,
          "standby_row_stable_idempotency": false,
          "standby_strict_monitor_wait_policy": false,
          "standby_timeout_still_waiting_treated_as_completion": false,
          "startup_local_rows_clean": false,
          "startup_prep_acks_clean": false,
          "startup_prep_cards_sent": false,
          "startup_scope_active": true,
          "startup_scope_reconciliation_checked": false,
          "startup_scope_reconciliation_clean": false,
          "stateful_postcondition_required": false,
          "status": "rejected",
          "terminal_reason": "invalid"
        }
      },
      "daemon_enqueues_past_barrier": {
        "detected": true,
        "expected_failure": "Router daemon enqueued work after a barrier",
        "failures": [
          "Router daemon enqueued work after a barrier"
        ],
        "state": {
          "barrier_active": true,
          "continuous_standby_row_present": false,
          "controller_action_table_exists": true,
          "controller_table_has_router_dependency_graph": false,
          "daemon_started": true,
          "daemon_tick_seconds": 1,
          "duplicate_controller_row_created": false,
          "enqueued_after_barrier": true,
          "foreground_controller_stopped_during_standby": false,
          "idempotency_key_used": false,
          "independent_controller_row_pending": false,
          "independent_row_enqueued": true,
          "live_wait_without_ordinary_controller_row": false,
          "next_independent_row_enqueued": false,
          "pm_activation_decision_accepted": false,
          "pm_activation_second_global_join_required": false,
          "pm_startup_activation_ack_clean": false,
          "pm_startup_activation_card_sent": false,
          "receipt_done": false,
          "reviewer_fact_report_recorded": false,
          "reviewer_startup_fact_review_started": false,
          "route_work_started": false,
          "router_marked_row_reconciled": false,
          "router_scheduler_table_exists": true,
          "router_table_has_dependency_metadata": true,
          "router_visible_postcondition_written": false,
          "scenario": "daemon_enqueues_past_barrier",
          "standby_codex_plan_item_in_progress": false,
          "standby_codex_plan_sync_required": false,
          "standby_completed_after_one_check": false,
          "standby_row_names_wait_target": false,
          "standby_row_stable_idempotency": false,
          "standby_strict_monitor_wait_policy": false,
          "standby_timeout_still_waiting_treated_as_completion": false,
          "startup_local_rows_clean": false,
          "startup_prep_acks_clean": false,
          "startup_prep_cards_sent": false,
          "startup_scope_active": true,
          "startup_scope_reconciliation_checked": false,
          "startup_scope_reconciliation_clean": false,
          "stateful_postcondition_required": false,
          "status": "rejected",
          "terminal_reason": "invalid"
        }
      },
      "live_wait_with_empty_controller_plan": {
        "detected": true,
        "expected_failure": "live daemon wait exposed an empty Controller plan instead of a continuous standby row",
        "failures": [
          "live daemon wait exposed an empty Controller plan instead of a continuous standby row"
        ],
        "state": {
          "barrier_active": true,
          "continuous_standby_row_present": false,
          "controller_action_table_exists": true,
          "controller_table_has_router_dependency_graph": false,
          "daemon_started": true,
          "daemon_tick_seconds": 1,
          "duplicate_controller_row_created": false,
          "enqueued_after_barrier": false,
          "foreground_controller_stopped_during_standby": false,
          "idempotency_key_used": false,
          "independent_controller_row_pending": false,
          "independent_row_enqueued": false,
          "live_wait_without_ordinary_controller_row": true,
          "next_independent_row_enqueued": false,
          "pm_activation_decision_accepted": false,
          "pm_activation_second_global_join_required": false,
          "pm_startup_activation_ack_clean": false,
          "pm_startup_activation_card_sent": false,
          "receipt_done": false,
          "reviewer_fact_report_recorded": false,
          "reviewer_startup_fact_review_started": false,
          "route_work_started": false,
          "router_marked_row_reconciled": false,
          "router_scheduler_table_exists": true,
          "router_table_has_dependency_metadata": true,
          "router_visible_postcondition_written": false,
          "scenario": "live_wait_with_empty_controller_plan",
          "standby_codex_plan_item_in_progress": false,
          "standby_codex_plan_sync_required": false,
          "standby_completed_after_one_check": false,
          "standby_row_names_wait_target": false,
          "standby_row_stable_idempotency": false,
          "standby_strict_monitor_wait_policy": false,
          "standby_timeout_still_waiting_treated_as_completion": false,
          "startup_local_rows_clean": false,
          "startup_prep_acks_clean": false,
          "startup_prep_cards_sent": false,
          "startup_scope_active": true,
          "startup_scope_reconciliation_checked": false,
          "startup_scope_reconciliation_clean": false,
          "stateful_postcondition_required": false,
          "status": "rejected",
          "terminal_reason": "invalid"
        }
      },
      "pm_activation_requires_second_global_join": {
        "detected": true,
        "expected_failure": "PM startup activation required redundant all-startup ACK join",
        "failures": [
          "PM startup activation required redundant all-startup ACK join"
        ],
        "state": {
          "barrier_active": false,
          "continuous_standby_row_present": false,
          "controller_action_table_exists": true,
          "controller_table_has_router_dependency_graph": false,
          "daemon_started": true,
          "daemon_tick_seconds": 1,
          "duplicate_controller_row_created": false,
          "enqueued_after_barrier": false,
          "foreground_controller_stopped_during_standby": false,
          "idempotency_key_used": false,
          "independent_controller_row_pending": false,
          "independent_row_enqueued": false,
          "live_wait_without_ordinary_controller_row": false,
          "next_independent_row_enqueued": false,
          "pm_activation_decision_accepted": false,
          "pm_activation_second_global_join_required": true,
          "pm_startup_activation_ack_clean": true,
          "pm_startup_activation_card_sent": true,
          "receipt_done": false,
          "reviewer_fact_report_recorded": true,
          "reviewer_startup_fact_review_started": false,
          "route_work_started": false,
          "router_marked_row_reconciled": false,
          "router_scheduler_table_exists": true,
          "router_table_has_dependency_metadata": true,
          "router_visible_postcondition_written": false,
          "scenario": "pm_activation_requires_second_global_join",
          "standby_codex_plan_item_in_progress": false,
          "standby_codex_plan_sync_required": false,
          "standby_completed_after_one_check": false,
          "standby_row_names_wait_target": false,
          "standby_row_stable_idempotency": false,
          "standby_strict_monitor_wait_policy": false,
          "standby_timeout_still_waiting_treated_as_completion": false,
          "startup_local_rows_clean": false,
          "startup_prep_acks_clean": false,
          "startup_prep_cards_sent": false,
          "startup_scope_active": true,
          "startup_scope_reconciliation_checked": false,
          "startup_scope_reconciliation_clean": false,
          "stateful_postcondition_required": false,
          "status": "rejected",
          "terminal_reason": "invalid"
        }
      },
      "reviewer_starts_before_startup_scope_clean": {
        "detected": true,
        "expected_failure": "Reviewer startup fact review started before startup current-scope reconciliation was clean",
        "failures": [
          "Reviewer startup fact review started before startup current-scope reconciliation was clean"
        ],
        "state": {
          "barrier_active": false,
          "continuous_standby_row_present": false,
          "controller_action_table_exists": true,
          "controller_table_has_router_dependency_graph": false,
          "daemon_started": true,
          "daemon_tick_seconds": 1,
          "duplicate_controller_row_created": false,
          "enqueued_after_barrier": false,
          "foreground_controller_stopped_during_standby": false,
          "idempotency_key_used": false,
          "independent_controller_row_pending": false,
          "independent_row_enqueued": false,
          "live_wait_without_ordinary_controller_row": false,
          "next_independent_row_enqueued": false,
          "pm_activation_decision_accepted": false,
          "pm_activation_second_global_join_required": false,
          "pm_startup_activation_ack_clean": false,
          "pm_startup_activation_card_sent": false,
          "receipt_done": false,
          "reviewer_fact_report_recorded": false,
          "reviewer_startup_fact_review_started": true,
          "route_work_started": false,
          "router_marked_row_reconciled": false,
          "router_scheduler_table_exists": true,
          "router_table_has_dependency_metadata": true,
          "router_visible_postcondition_written": false,
          "scenario": "reviewer_starts_before_startup_scope_clean",
          "standby_codex_plan_item_in_progress": false,
          "standby_codex_plan_sync_required": false,
          "standby_completed_after_one_check": false,
          "standby_row_names_wait_target": false,
          "standby_row_stable_idempotency": false,
          "standby_strict_monitor_wait_policy": false,
          "standby_timeout_still_waiting_treated_as_completion": false,
          "startup_local_rows_clean": false,
          "startup_prep_acks_clean": false,
          "startup_prep_cards_sent": true,
          "startup_scope_active": true,
          "startup_scope_reconciliation_checked": false,
          "startup_scope_reconciliation_clean": false,
          "stateful_postcondition_required": false,
          "status": "rejected",
          "terminal_reason": "invalid"
        }
      },
      "standby_completes_after_one_check": {
        "detected": true,
        "expected_failure": "continuous standby row was completed after one monitor check",
        "failures": [
          "continuous standby row does not keep Codex plan sync in progress",
          "continuous standby row does not require strict monitor wait timing",
          "continuous standby row was completed after one monitor check",
          "foreground Controller stopped during a live continuous standby duty"
        ],
        "state": {
          "barrier_active": true,
          "continuous_standby_row_present": true,
          "controller_action_table_exists": true,
          "controller_table_has_router_dependency_graph": false,
          "daemon_started": true,
          "daemon_tick_seconds": 1,
          "duplicate_controller_row_created": false,
          "enqueued_after_barrier": false,
          "foreground_controller_stopped_during_standby": true,
          "idempotency_key_used": false,
          "independent_controller_row_pending": false,
          "independent_row_enqueued": false,
          "live_wait_without_ordinary_controller_row": true,
          "next_independent_row_enqueued": false,
          "pm_activation_decision_accepted": false,
          "pm_activation_second_global_join_required": false,
          "pm_startup_activation_ack_clean": false,
          "pm_startup_activation_card_sent": false,
          "receipt_done": false,
          "reviewer_fact_report_recorded": false,
          "reviewer_startup_fact_review_started": false,
          "route_work_started": false,
          "router_marked_row_reconciled": false,
          "router_scheduler_table_exists": true,
          "router_table_has_dependency_metadata": true,
          "router_visible_postcondition_written": false,
          "scenario": "standby_completes_after_one_check",
          "standby_codex_plan_item_in_progress": false,
          "standby_codex_plan_sync_required": true,
          "standby_completed_after_one_check": true,
          "standby_row_names_wait_target": true,
          "standby_row_stable_idempotency": true,
          "standby_strict_monitor_wait_policy": false,
          "standby_timeout_still_waiting_treated_as_completion": false,
          "startup_local_rows_clean": false,
          "startup_prep_acks_clean": false,
          "startup_prep_cards_sent": false,
          "startup_scope_active": true,
          "startup_scope_reconciliation_checked": false,
          "startup_scope_reconciliation_clean": false,
          "stateful_postcondition_required": false,
          "status": "rejected",
          "terminal_reason": "invalid"
        }
      },
      "standby_timeout_treated_as_completion": {
        "detected": true,
        "expected_failure": "timeout_still_waiting was treated as standby completion",
        "failures": [
          "continuous standby row does not keep Codex plan sync in progress",
          "continuous standby row does not require strict monitor wait timing",
          "timeout_still_waiting was treated as standby completion",
          "foreground Controller stopped during a live continuous standby duty"
        ],
        "state": {
          "barrier_active": true,
          "continuous_standby_row_present": true,
          "controller_action_table_exists": true,
          "controller_table_has_router_dependency_graph": false,
          "daemon_started": true,
          "daemon_tick_seconds": 1,
          "duplicate_controller_row_created": false,
          "enqueued_after_barrier": false,
          "foreground_controller_stopped_during_standby": true,
          "idempotency_key_used": false,
          "independent_controller_row_pending": false,
          "independent_row_enqueued": false,
          "live_wait_without_ordinary_controller_row": true,
          "next_independent_row_enqueued": false,
          "pm_activation_decision_accepted": false,
          "pm_activation_second_global_join_required": false,
          "pm_startup_activation_ack_clean": false,
          "pm_startup_activation_card_sent": false,
          "receipt_done": false,
          "reviewer_fact_report_recorded": false,
          "reviewer_startup_fact_review_started": false,
          "route_work_started": false,
          "router_marked_row_reconciled": false,
          "router_scheduler_table_exists": true,
          "router_table_has_dependency_metadata": true,
          "router_visible_postcondition_written": false,
          "scenario": "standby_timeout_treated_as_completion",
          "standby_codex_plan_item_in_progress": false,
          "standby_codex_plan_sync_required": true,
          "standby_completed_after_one_check": false,
          "standby_row_names_wait_target": true,
          "standby_row_stable_idempotency": true,
          "standby_strict_monitor_wait_policy": false,
          "standby_timeout_still_waiting_treated_as_completion": true,
          "startup_local_rows_clean": false,
          "startup_prep_acks_clean": false,
          "startup_prep_cards_sent": false,
          "startup_scope_active": true,
          "startup_scope_reconciliation_checked": false,
          "startup_scope_reconciliation_clean": false,
          "stateful_postcondition_required": false,
          "status": "rejected",
          "terminal_reason": "invalid"
        }
      },
      "stateful_receipt_cleared_without_postcondition": {
        "detected": true,
        "expected_failure": "Router reconciled stateful receipt without Router-visible postcondition evidence",
        "failures": [
          "Router reconciled stateful receipt without Router-visible postcondition evidence"
        ],
        "state": {
          "barrier_active": false,
          "continuous_standby_row_present": false,
          "controller_action_table_exists": true,
          "controller_table_has_router_dependency_graph": false,
          "daemon_started": true,
          "daemon_tick_seconds": 1,
          "duplicate_controller_row_created": false,
          "enqueued_after_barrier": false,
          "foreground_controller_stopped_during_standby": false,
          "idempotency_key_used": false,
          "independent_controller_row_pending": false,
          "independent_row_enqueued": false,
          "live_wait_without_ordinary_controller_row": false,
          "next_independent_row_enqueued": false,
          "pm_activation_decision_accepted": false,
          "pm_activation_second_global_join_required": false,
          "pm_startup_activation_ack_clean": false,
          "pm_startup_activation_card_sent": false,
          "receipt_done": true,
          "reviewer_fact_report_recorded": false,
          "reviewer_startup_fact_review_started": false,
          "route_work_started": false,
          "router_marked_row_reconciled": true,
          "router_scheduler_table_exists": true,
          "router_table_has_dependency_metadata": true,
          "router_visible_postcondition_written": false,
          "scenario": "stateful_receipt_cleared_without_postcondition",
          "standby_codex_plan_item_in_progress": false,
          "standby_codex_plan_sync_required": false,
          "standby_completed_after_one_check": false,
          "standby_row_names_wait_target": false,
          "standby_row_stable_idempotency": false,
          "standby_strict_monitor_wait_policy": false,
          "standby_timeout_still_waiting_treated_as_completion": false,
          "startup_local_rows_clean": false,
          "startup_prep_acks_clean": false,
          "startup_prep_cards_sent": false,
          "startup_scope_active": true,
          "startup_scope_reconciliation_checked": false,
          "startup_scope_reconciliation_clean": false,
          "stateful_postcondition_required": true,
          "status": "rejected",
          "terminal_reason": "invalid"
        }
      }
    },
    "ok": true
  },
  "model_boundary": "focused Router scheduler/Controller table/startup gate model; runtime tests remain required; heavyweight meta/capability checks intentionally skipped",
  "ok": true,
  "progress": {
    "cannot_reach_terminal_count": 0,
    "ok": true,
    "samples": [],
    "stuck_state_count": 0
  },
  "safe_graph": {
    "accepted_scenarios": [
      "async_startup_rows_until_barrier",
      "continuous_standby_row_during_live_wait",
      "controller_table_simple_router_table_complex",
      "pm_activation_same_role_ack_only",
      "startup_review_waits_for_current_scope_reconciliation",
      "stateful_receipt_reconciled_with_postcondition"
    ],
    "edge_count": 30,
    "invariant_failure_count": 0,
    "invariant_failures": [],
    "missing_labels": [],
    "ok": true,
    "rejected_scenarios": [
      "controller_owns_router_dependencies",
      "daemon_duplicates_controller_row_on_retry",
      "daemon_enqueues_past_barrier",
      "live_wait_with_empty_controller_plan",
      "pm_activation_requires_second_global_join",
      "reviewer_starts_before_startup_scope_clean",
      "standby_completes_after_one_check",
      "standby_timeout_treated_as_completion",
      "stateful_receipt_cleared_without_postcondition"
    ],
    "state_count": 31
  }
}
